README.rst
setup.py
miura/__init__.py
miura/data.py
miura/exceptions.py
miura/runner.py
miura/script.py
miura/template.py
miura/utils.py
miura.egg-info/PKG-INFO
miura.egg-info/SOURCES.txt
miura.egg-info/dependency_links.txt
miura.egg-info/entry_points.txt
miura.egg-info/requires.txt
miura.egg-info/top_level.txt