Metadata-Version: 1.1
Name: miura
Version: 0.0.1
Summary: a Jenkins job management tool
Home-page: http://toumorokoshi.github.io/miura
Author: Yusuke Tsutsumi
Author-email: yusuke@yusuketsutsumi.com
License: UNKNOWN
Platform: UNKNOWN
Classifier: Development Status :: 2 - Pre-Alpha
Classifier: Topic :: System :: Software Distribution
Classifier: License :: OSI Approved :: MIT License
Classifier: Programming Language :: Python
Classifier: Programming Language :: Python :: 2.6
Classifier: Programming Language :: Python :: 2.7
